Metadata-Version: 2.1
Name: rudi
Version: 1.0
Summary: Small, fast and simple Python CLI image converter for CNNs.
Home-page: https://github.com/liashchynskyi/rudi
Author: Petro Liashchynskyi
License: UNKNOWN
Platform: UNKNOWN
Classifier: Programming Language :: Python :: 3
Classifier: License :: OSI Approved :: MIT License
Classifier: Operating System :: OS Independent
